PyBLEz/__init__.py
PyBLEz/advertisement.py
PyBLEz/agent.py
PyBLEz/application.py
PyBLEz/characteristic.py
PyBLEz/core.py
PyBLEz/descriptor.py
PyBLEz/logger.py
PyBLEz/service.py
PyBLEz-0.2.3.dist-info/LICENSE
PyBLEz-0.2.3.dist-info/METADATA
PyBLEz-0.2.3.dist-info/WHEEL
PyBLEz-0.2.3.dist-info/top_level.txt
PyBLEz-0.2.3.dist-info/RECORD
