Metadata-Version: 2.1
Name: PyBLEz
Version: 0.2.3
Summary: A Python library for creating BLE peripherals using BlueZ and D-Bus
Home-page: https://github.com/kgoke/PyBLEz
Author: Keegan Goecke
Author-email: goecke.dev@gmail.com
License: MIT
Requires-Python: >=3.6
License-File: LICENSE
Requires-Dist: dbus-python
Requires-Dist: pycairo
Requires-Dist: pygobject
